pelican/plugins/more_categories/__init__.py
pelican/plugins/more_categories/more_categories.py
pelican/plugins/more_categories/test_data/article_with_multiple_categories.rst
pelican/plugins/more_categories/test_data/article_with_no_category.rst
pelican/plugins/more_categories/test_more_categories.py
pelican_more_categories-0.1.0.dist-info/LICENSE
pelican_more_categories-0.1.0.dist-info/WHEEL
pelican_more_categories-0.1.0.dist-info/METADATA
pelican_more_categories-0.1.0.dist-info/RECORD
