Metadata-Version: 2.1
Name: pelican-more-categories
Version: 0.1.0
Summary: Enables nested categories and multiple categories per article
Home-page: https://github.com/pelican-plugins/more-categories
License: AGPL-3.0
Keywords: pelican,plugin
Author: Oliver Urs Lenz
Author-email: oliver.urs.lenz@gmail.com
Requires-Python: >=3.6,<4.0
Classifier: Development Status :: 5 - Production/Stable
Classifier: Environment :: Console
Classifier: Framework :: Pelican
Classifier: Framework :: Pelican :: Plugins
Classifier: Intended Audience :: End Users/Desktop
Classifier: License :: OSI Approved :: GNU Affero General Public License v3
Classifier: Operating System :: OS Independent
Classifier: Programming Language :: Python
Classifier: Programming Language :: Python :: 3
Classifier: Programming Language :: Python :: 3.6
Classifier: Programming Language :: Python :: 3.7
Classifier: Programming Language :: Python :: 3.8
Classifier: Programming Language :: Python :: 3.9
Classifier: Topic :: Internet :: WWW/HTTP
Classifier: Topic :: Software Development :: Libraries :: Python Modules
Provides-Extra: markdown
Requires-Dist: markdown (>=3.1.1,<4.0.0); extra == "markdown"
Requires-Dist: pelican (>=4.2,<5.0)
Project-URL: Documentation, https://docs.getpelican.com/
Project-URL: Funding, https://donate.getpelican.com/
Project-URL: Repository, https://github.com/pelican-plugins/more-categories
Project-URL: Source, https://github.com/pelican-plugins/more-categories
Project-URL: Tracker, https://github.com/pelican-plugins/more-categories/issues
